devlog/__init__.py
devlog/custom_excepthook.py
devlog/decorator.py
python_devlog-1.2.dist-info/LICENSE.txt
python_devlog-1.2.dist-info/METADATA
python_devlog-1.2.dist-info/WHEEL
python_devlog-1.2.dist-info/top_level.txt
python_devlog-1.2.dist-info/RECORD
