Metadata-Version: 2.1
Name: python-devlog
Version: 1.2
Summary: No more logging in your code business logic with decorators
Home-page: https://github.com/MeGaNeKoS/devlog
Author: めがねこ
Author-email: evictory91@gmail.com
License: MIT
Keywords: clean code,decorators,logging
Classifier: Development Status :: 5 - Production/Stable
Classifier: Intended Audience :: Developers
Classifier: License :: OSI Approved :: MIT License
Classifier: Programming Language :: Python :: 3
License-File: LICENSE.txt
